demoahm23/__init__.py
demoahm23/hello.py
demoahm23-0.4.dist-info/LICENSE
demoahm23-0.4.dist-info/METADATA
demoahm23-0.4.dist-info/WHEEL
demoahm23-0.4.dist-info/top_level.txt
demoahm23-0.4.dist-info/RECORD
