Metadata-Version: 2.1
Name: demoahm23
Version: 0.4
Summary: A sample python project for the NeIC AHM23 workshop
Author-email: JMuff22 <67475147+JMuff22@users.noreply.github.com>
License: MIT License
Project-URL: Homepage, https://github.com/JMuff22/neic-ahm23-releasing-a-python-package
Project-URL: Bug Tracker, https://github.com/JMuff22/neic-ahm23-releasing-a-python-package/issues
Classifier: Programming Language :: Python :: 3
Classifier: License :: OSI Approved :: MIT License
Classifier: Operating System :: OS Independent
Classifier: Development Status :: 3 - Alpha
Requires-Python: >=3.7
License-File: LICENSE
Requires-Dist: requests (>=2.26.0)
Provides-Extra: dev
Requires-Dist: tox (==3.26.0) ; extra == 'dev'
Requires-Dist: black (==22.10.0) ; extra == 'dev'
Requires-Dist: twine (<4.0,>=3.8.0) ; extra == 'dev'
Requires-Dist: wheel (<1.0,>=0.37.1) ; extra == 'dev'
Requires-Dist: pytest ; extra == 'dev'
